
[
    {
        "title": "Metropolis Pt. 2",
        "author": "Dream Theater",
        "year": 1999,
        "poster": "https://i.discogs.com/8hNrwPVUU5iHy04bTb3pskoOW2RFZy0nCdW5LhX-cYk/rs:fit/g:sm/q:90/h:600/w:600/czM6Ly9kaXNjb2dz/LWRhdGFiYXNlLWlt/YWdlcy9SLTIxMTA3/NDQtMTQ5NDM1NTk4/Mi0xMzI1LmpwZWc.jpeg",
        "genre": "Rock"
    },
    {
        "title": "Live at Wembley 86",
        "author": "Queen",
        "year": 1992,
        "poster": "https://images-na.ssl-images-amazon.com/images/I/71g40mlbinL._SX355_.jpg",
        "genre": "Pop"
    },
    {
        "title": "American Idiot",
        "author": "Green Day",
        "year": 2004,
        "poster": "https://m.media-amazon.com/images/I/71Z0rLIvpuL._UF1000,1000_QL80_.jpg",
        "genre": "Rock alternativo"
    },
    {
        "title": "Minutes to Midnight",
        "author": "Linkin Park",
        "year": 2007,
        "poster": "https://i.discogs.com/P6rqfF1MmH2pVGHxNy6YCsX-OtCcDgNGbj3ZtdE90hI/rs:fit/g:sm/q:90/h:600/w:600/czM6Ly9kaXNjb2dz/LWRhdGFiYXNlLWlt/YWdlcy9SLTE4OTYw/NDUtMTI2NDg0NzAz/MS5qcGVn.jpeg",
        "genre": "Alternative rock"
    },
    {
        "title": "Brave new World",
        "author": "Iron Maiden",
        "year": 2000,
        "poster": "https://upload.wikimedia.org/wikipedia/en/0/03/Iron_Maiden_-_Brave_New_World.jpg",
        "genre": "Metal"
    },
    {
        "title": "The Wall",
        "author": "Pink Floyd",
        "year": 1979,
        "poster": "https://i.scdn.co/image/ab67616d0000b2735d48e2f56d691f9a4e4b0bdf",
        "genre": "Progressive Rock"
    }
]

